umlio/IOTypes.py
umlio/Reader.py
umlio/Writer.py
umlio/XMLConstants.py
umlio/__init__.py
umlio/_version.py
umlio/py.typed
umlio/deserializer/XmlActorsToUmlActors.py
umlio/deserializer/XmlClassesToUmlClasses.py
umlio/deserializer/XmlLinksToUmlLinks.py
umlio/deserializer/XmlLollipopsToUmlLollipops.py
umlio/deserializer/XmlNotesToUmlNotes.py
umlio/deserializer/XmlTextsToUmlTexts.py
umlio/deserializer/XmlToUmlModel.py
umlio/deserializer/XmlToUmlShapes.py
umlio/deserializer/XmlUseCasesToUmlUseCases.py
umlio/deserializer/__init__.py
umlio/deserializer/py.typed
umlio/exceptions/UnsupportedFileTypeException.py
umlio/exceptions/UnsupportedVersion.py
umlio/exceptions/__init__.py
umlio/exceptions/py.typed
umlio/resources/__init__.py
umlio/resources/loggingConfiguration.json
umlio/resources/py.typed
umlio/serializer/BaseUmlToXml.py
umlio/serializer/UmlClassToXml.py
umlio/serializer/UmlLinksToXml.py
umlio/serializer/UmlLollipopsToXml.py
umlio/serializer/UmlModelToXml.py
umlio/serializer/UmlNotesToXml.py
umlio/serializer/UmlShapesToXml.py
umlio/serializer/UmlTextsToXml.py
umlio/serializer/UmlUseCasesToXml.py
umlio/serializer/__init__.py
umlio/serializer/py.typed
umlio-0.6.0.dist-info/licenses/LICENSE
umlio-0.6.0.dist-info/METADATA
umlio-0.6.0.dist-info/WHEEL
umlio-0.6.0.dist-info/entry_points.txt
umlio-0.6.0.dist-info/top_level.txt
umlio-0.6.0.dist-info/RECORD
