Metadata-Version: 2.4
Name: umlio
Version: 0.6.0
Summary: serialize deserialize umlshapes
Author-email: "Humberto A. Sanchez II" <Humberto.A.Sanchez.II@gmail.com>
Maintainer-email: "Humberto A. Sanchez II" <Humberto.A.Sanchez.II@gmail.com>
License-Expression: AGPL-1.0-or-later
Project-URL: Repository, https://github.com/hasii2011/umlio
Keywords: pyut,graphical shapes,python
License-File: LICENSE
Requires-Dist: untangle==1.2.1
Requires-Dist: codeallybasic>=1.30.0
Requires-Dist: codeallyadvanced>=2.3.0
Requires-Dist: umlmodel>=3.4.0
Requires-Dist: umlshapes>=1.5.0
Requires-Dist: Pypubsub==4.0.3
Provides-Extra: test
Requires-Dist: mypy==1.19.1; extra == "test"
Requires-Dist: mypy-extensions==1.0.0; extra == "test"
Requires-Dist: types-Deprecated==1.3.1.20251101; extra == "test"
Requires-Dist: html-testRunner~=1.2.1; extra == "test"
Requires-Dist: human_id==0.2.0; extra == "test"
Provides-Extra: deploy
Requires-Dist: wheel==0.45.1; extra == "deploy"
Requires-Dist: setuptools==80.9.0; extra == "deploy"
Requires-Dist: twine==6.1.0; extra == "deploy"
Requires-Dist: build==1.3.0; extra == "deploy"
Dynamic: license-file
